httpea/__init__.py
httpea/http_body.py
httpea/http_cookies.py
httpea/http_error.py
httpea/http_headers.py
httpea/http_message.py
httpea/http_method.py
httpea/http_multipart_message_parser.py
httpea/http_parsed_body.py
httpea/http_query_string.py
httpea/http_request.py
httpea/http_response.py
httpea/http_status.py
httpea/router.py
httpea-1.0.0.dist-info/LICENSE
httpea-1.0.0.dist-info/METADATA
httpea-1.0.0.dist-info/WHEEL
httpea-1.0.0.dist-info/RECORD
